shopify_abandoned_checkout/__init__.py
shopify_abandoned_checkout/admin.py
shopify_abandoned_checkout/apps.py
shopify_abandoned_checkout/management/__init__.py
shopify_abandoned_checkout/management/commands/__init__.py
shopify_abandoned_checkout/management/commands/send_shopify_abandoned_checkouts.py
shopify_abandoned_checkout/migrations/0001_initial.py
shopify_abandoned_checkout/migrations/0002_auto_20191108_1748.py
shopify_abandoned_checkout/migrations/__init__.py
shopify_abandoned_checkout/models.py
shopify_abandoned_checkout/tasks.py
shopify_abandoned_checkout/templates/email/abandoned_checkout.html
shopify_abandoned_checkout/templates/email/abandoned_checkout.txt
shopify_abandoned_checkout/tests.py
shopify_abandoned_checkout/utils.py
django_shopify_abandoned_checkout-0.0.8.dist-info/LICENSE
django_shopify_abandoned_checkout-0.0.8.dist-info/WHEEL
django_shopify_abandoned_checkout-0.0.8.dist-info/METADATA
django_shopify_abandoned_checkout-0.0.8.dist-info/RECORD
